jhelper/.mypy_cache/.gitignore
jhelper/.mypy_cache/3.8/@plugins_snapshot.json
jhelper/.mypy_cache/3.8/_ast.data.json
jhelper/.mypy_cache/3.8/_ast.meta.json
jhelper/.mypy_cache/3.8/_csv.data.json
jhelper/.mypy_cache/3.8/_csv.meta.json
jhelper/.mypy_cache/3.8/_importlib_modulespec.data.json
jhelper/.mypy_cache/3.8/_importlib_modulespec.meta.json
jhelper/.mypy_cache/3.8/_random.data.json
jhelper/.mypy_cache/3.8/_random.meta.json
jhelper/.mypy_cache/3.8/_thread.data.json
jhelper/.mypy_cache/3.8/_thread.meta.json
jhelper/.mypy_cache/3.8/_typeshed/__init__.data.json
jhelper/.mypy_cache/3.8/_typeshed/__init__.meta.json
jhelper/.mypy_cache/3.8/abc.data.json
jhelper/.mypy_cache/3.8/abc.meta.json
jhelper/.mypy_cache/3.8/argparse.data.json
jhelper/.mypy_cache/3.8/argparse.meta.json
jhelper/.mypy_cache/3.8/array.data.json
jhelper/.mypy_cache/3.8/array.meta.json
jhelper/.mypy_cache/3.8/ast.data.json
jhelper/.mypy_cache/3.8/ast.meta.json
jhelper/.mypy_cache/3.8/builtins.data.json
jhelper/.mypy_cache/3.8/builtins.meta.json
jhelper/.mypy_cache/3.8/codecs.data.json
jhelper/.mypy_cache/3.8/codecs.meta.json
jhelper/.mypy_cache/3.8/collections/__init__.data.json
jhelper/.mypy_cache/3.8/collections/__init__.meta.json
jhelper/.mypy_cache/3.8/csv.data.json
jhelper/.mypy_cache/3.8/csv.meta.json
jhelper/.mypy_cache/3.8/datetime.data.json
jhelper/.mypy_cache/3.8/datetime.meta.json
jhelper/.mypy_cache/3.8/email/__init__.data.json
jhelper/.mypy_cache/3.8/email/__init__.meta.json
jhelper/.mypy_cache/3.8/email/charset.data.json
jhelper/.mypy_cache/3.8/email/charset.meta.json
jhelper/.mypy_cache/3.8/email/contentmanager.data.json
jhelper/.mypy_cache/3.8/email/contentmanager.meta.json
jhelper/.mypy_cache/3.8/email/errors.data.json
jhelper/.mypy_cache/3.8/email/errors.meta.json
jhelper/.mypy_cache/3.8/email/header.data.json
jhelper/.mypy_cache/3.8/email/header.meta.json
jhelper/.mypy_cache/3.8/email/message.data.json
jhelper/.mypy_cache/3.8/email/message.meta.json
jhelper-0.1.1.dist-info/entry_points.txt
jhelper-0.1.1.dist-info/WHEEL
jhelper-0.1.1.dist-info/METADATA
jhelper-0.1.1.dist-info/RECORD
